{
    "info": {
        "id": 14600303,
        "type": "VT",
        "material": "ST"
    },
    "image_data": {
        "file_name": "VT_ST_02_14600303",
        "format": "jpg",
        "information": "기공",
        "width": 1280,
        "height": 720
    },
    "meta": {
        "is_crowd": 0,
        "annotation_case": [
            "porosity"
        ],
        "total_case": [
            "porosity",
            "porosity",
            "porosity",
            "porosity",
            "porosity",
            "porosity",
            "porosity",
            "porosity",
            "porosity",
            "porosity",
            "porosity",
            "porosity",
            "porosity",
            "porosity",
            "porosity",
            "porosity",
            "porosity",
            "porosity"
        ]
    },
    "annotations": [
        {
            "tool": "polygon",
            "coordinate": {
                "x": [
                    851,
                    855,
                    859,
                    865,
                    869,
                    871,
                    876,
                    882,
                    886,
                    887,
                    887,
                    886,
                    884,
                    881,
                    876,
                    872,
                    868,
                    865,
                    861,
                    858,
                    855,
                    853,
                    850,
                    848,
                    848,
                    849
                ],
                "y": [
                    146,
                    148,
                    149,
                    149,
                    149,
                    152,
                    156,
                    160,
                    163,
                    166,
                    170,
                    173,
                    174,
                    174,
                    173,
                    171,
                    170,
                    170,
                    167,
                    166,
                    164,
                    161,
                    159,
                    158,
                    154,
                    149
                ]
            },
            "class": "defect",
            "case": "porosity"
        },
        {
            "tool": "polygon",
            "coordinate": {
                "x": [
                    916,
                    917,
                    919,
                    921,
                    925,
                    931,
                    935,
                    938,
                    937,
                    937,
                    935,
                    931,
                    927,
                    924,
                    922
                ],
                "y": [
                    147,
                    154,
                    159,
                    165,
                    170,
                    173,
                    173,
                    171,
                    166,
                    162,
                    159,
                    155,
                    151,
                    148,
                    145
                ]
            },
            "class": "defect",
            "case": "porosity"
        },
        {
            "tool": "polygon",
            "coordinate": {
                "x": [
                    915,
                    913,
                    915,
                    920,
                    922,
                    924,
                    926,
                    931,
                    933,
                    933,
                    931,
                    930,
                    932,
                    935,
                    939,
                    940,
                    941,
                    941,
                    939,
                    937,
                    938,
                    938,
                    937,
                    937,
                    933,
                    928,
                    925,
                    921,
                    917,
                    915
                ],
                "y": [
                    131,
                    135,
                    138,
                    139,
                    141,
                    143,
                    144,
                    144,
                    143,
                    145,
                    148,
                    148,
                    150,
                    151,
                    149,
                    147,
                    144,
                    142,
                    138,
                    135,
                    131,
                    126,
                    124,
                    122,
                    122,
                    122,
                    122,
                    125,
                    129,
                    131
                ]
            },
            "class": "defect",
            "case": "porosity"
        },
        {
            "tool": "polygon",
            "coordinate": {
                "x": [
                    786,
                    789,
                    793,
                    799,
                    801,
                    802,
                    802,
                    803,
                    803,
                    801,
                    798,
                    795,
                    793,
                    789,
                    787
                ],
                "y": [
                    435,
                    432,
                    429,
                    427,
                    428,
                    430,
                    434,
                    436,
                    439,
                    441,
                    443,
                    444,
                    443,
                    440,
                    438
                ]
            },
            "class": "defect",
            "case": "porosity"
        },
        {
            "tool": "polygon",
            "coordinate": {
                "x": [
                    819,
                    835,
                    845,
                    857,
                    865,
                    870,
                    867,
                    867,
                    873,
                    873,
                    864,
                    857,
                    848,
                    840,
                    837,
                    831,
                    826,
                    821,
                    818
                ],
                "y": [
                    427,
                    428,
                    430,
                    436,
                    438,
                    443,
                    453,
                    456,
                    461,
                    464,
                    469,
                    475,
                    477,
                    473,
                    463,
                    457,
                    454,
                    450,
                    447
                ]
            },
            "class": "defect",
            "case": "porosity"
        },
        {
            "tool": "polygon",
            "coordinate": {
                "x": [
                    824,
                    831,
                    840,
                    846,
                    853,
                    858,
                    862,
                    864,
                    864,
                    861,
                    852,
                    842,
                    832
                ],
                "y": [
                    502,
                    511,
                    514,
                    521,
                    533,
                    539,
                    541,
                    529,
                    517,
                    509,
                    504,
                    502,
                    500
                ]
            },
            "class": "defect",
            "case": "porosity"
        },
        {
            "tool": "polygon",
            "coordinate": {
                "x": [
                    896,
                    909,
                    921,
                    938,
                    946,
                    952,
                    958,
                    960,
                    960,
                    960,
                    959,
                    958,
                    954,
                    947,
                    937,
                    929,
                    922,
                    909,
                    900,
                    891
                ],
                "y": [
                    498,
                    500,
                    503,
                    505,
                    507,
                    512,
                    517,
                    522,
                    530,
                    535,
                    542,
                    546,
                    551,
                    555,
                    543,
                    531,
                    529,
                    520,
                    513,
                    506
                ]
            },
            "class": "defect",
            "case": "porosity"
        },
        {
            "tool": "polygon",
            "coordinate": {
                "x": [
                    851,
                    854,
                    869,
                    878,
                    894,
                    902,
                    903,
                    902,
                    901,
                    900,
                    898,
                    894,
                    889,
                    880,
                    870,
                    860,
                    855,
                    851
                ],
                "y": [
                    621,
                    605,
                    597,
                    596,
                    600,
                    603,
                    607,
                    613,
                    621,
                    627,
                    631,
                    634,
                    637,
                    640,
                    639,
                    639,
                    636,
                    631
                ]
            },
            "class": "defect",
            "case": "porosity"
        },
        {
            "tool": "polygon",
            "coordinate": {
                "x": [
                    1027,
                    1032,
                    1039,
                    1048,
                    1052,
                    1045,
                    1039,
                    1036,
                    1034,
                    1030
                ],
                "y": [
                    692,
                    681,
                    676,
                    674,
                    676,
                    685,
                    691,
                    696,
                    699,
                    699
                ]
            },
            "class": "defect",
            "case": "porosity"
        },
        {
            "tool": "polygon",
            "coordinate": {
                "x": [
                    1044,
                    1044,
                    1047,
                    1053,
                    1058,
                    1063,
                    1069,
                    1069,
                    1072,
                    1080,
                    1089,
                    1094,
                    1099,
                    1103,
                    1104,
                    1103,
                    1102,
                    1098,
                    1092,
                    1087,
                    1081,
                    1074,
                    1067,
                    1059,
                    1054,
                    1044
                ],
                "y": [
                    623,
                    615,
                    610,
                    604,
                    598,
                    594,
                    591,
                    596,
                    599,
                    601,
                    609,
                    611,
                    615,
                    618,
                    623,
                    627,
                    630,
                    631,
                    632,
                    632,
                    633,
                    633,
                    632,
                    630,
                    628,
                    624
                ]
            },
            "class": "defect",
            "case": "porosity"
        },
        {
            "tool": "polygon",
            "coordinate": {
                "x": [
                    1096,
                    1101,
                    1103,
                    1106,
                    1111,
                    1115,
                    1121,
                    1123,
                    1123,
                    1122,
                    1121,
                    1122,
                    1122,
                    1119,
                    1115,
                    1112,
                    1110,
                    1106,
                    1101
                ],
                "y": [
                    606,
                    600,
                    594,
                    587,
                    583,
                    579,
                    577,
                    581,
                    585,
                    589,
                    593,
                    597,
                    601,
                    603,
                    606,
                    609,
                    610,
                    611,
                    610
                ]
            },
            "class": "defect",
            "case": "porosity"
        },
        {
            "tool": "polygon",
            "coordinate": {
                "x": [
                    1022,
                    1026,
                    1032,
                    1043,
                    1052,
                    1056,
                    1056,
                    1055,
                    1053,
                    1051,
                    1047,
                    1043,
                    1040,
                    1032,
                    1027,
                    1025
                ],
                "y": [
                    573,
                    567,
                    562,
                    553,
                    557,
                    564,
                    570,
                    578,
                    582,
                    585,
                    589,
                    590,
                    590,
                    588,
                    587,
                    582
                ]
            },
            "class": "defect",
            "case": "porosity"
        },
        {
            "tool": "polygon",
            "coordinate": {
                "x": [
                    1078,
                    1084,
                    1090,
                    1093,
                    1098,
                    1103,
                    1108,
                    1108,
                    1106,
                    1102,
                    1096,
                    1092,
                    1087,
                    1086,
                    1080,
                    1078
                ],
                "y": [
                    532,
                    531,
                    531,
                    528,
                    528,
                    528,
                    531,
                    536,
                    539,
                    543,
                    546,
                    548,
                    543,
                    539,
                    537,
                    535
                ]
            },
            "class": "defect",
            "case": "porosity"
        },
        {
            "tool": "polygon",
            "coordinate": {
                "x": [
                    1086,
                    1086,
                    1086,
                    1091,
                    1095,
                    1100,
                    1101,
                    1103,
                    1103,
                    1102,
                    1101,
                    1101,
                    1098,
                    1095,
                    1090
                ],
                "y": [
                    514,
                    507,
                    501,
                    495,
                    494,
                    496,
                    500,
                    502,
                    505,
                    507,
                    509,
                    513,
                    514,
                    515,
                    516
                ]
            },
            "class": "defect",
            "case": "porosity"
        },
        {
            "tool": "polygon",
            "coordinate": {
                "x": [
                    1055,
                    1057,
                    1060,
                    1066,
                    1074,
                    1083,
                    1087,
                    1089,
                    1091,
                    1091,
                    1090,
                    1084,
                    1081,
                    1077,
                    1074,
                    1069,
                    1061
                ],
                "y": [
                    486,
                    473,
                    467,
                    463,
                    462,
                    462,
                    468,
                    472,
                    477,
                    479,
                    482,
                    484,
                    486,
                    487,
                    490,
                    492,
                    490
                ]
            },
            "class": "defect",
            "case": "porosity"
        },
        {
            "tool": "polygon",
            "coordinate": {
                "x": [
                    896,
                    901,
                    908,
                    913,
                    915,
                    917,
                    918,
                    918,
                    916,
                    916,
                    913,
                    909,
                    905,
                    900,
                    898,
                    895,
                    893,
                    893,
                    893
                ],
                "y": [
                    445,
                    444,
                    449,
                    453,
                    458,
                    462,
                    466,
                    470,
                    474,
                    478,
                    479,
                    474,
                    470,
                    465,
                    464,
                    461,
                    454,
                    450,
                    448
                ]
            },
            "class": "defect",
            "case": "porosity"
        },
        {
            "tool": "polygon",
            "coordinate": {
                "x": [
                    928,
                    925,
                    921,
                    925,
                    930,
                    937,
                    946,
                    952,
                    960,
                    967,
                    973,
                    978,
                    984,
                    991,
                    992,
                    997,
                    1001,
                    1005,
                    1010,
                    1012,
                    1017,
                    1018,
                    1019,
                    1012,
                    1004,
                    996,
                    988,
                    981,
                    969,
                    959,
                    952,
                    945,
                    935,
                    929
                ],
                "y": [
                    483,
                    462,
                    446,
                    438,
                    429,
                    425,
                    422,
                    420,
                    420,
                    421,
                    425,
                    427,
                    429,
                    430,
                    429,
                    430,
                    432,
                    436,
                    442,
                    448,
                    454,
                    460,
                    463,
                    468,
                    473,
                    478,
                    482,
                    486,
                    494,
                    495,
                    496,
                    495,
                    492,
                    488
                ]
            },
            "class": "defect",
            "case": "porosity"
        },
        {
            "tool": "polygon",
            "coordinate": {
                "x": [
                    969,
                    988,
                    993,
                    1006,
                    1015,
                    1028,
                    1033,
                    1040,
                    1039,
                    1038,
                    1037,
                    1035,
                    1029,
                    1022,
                    1015,
                    1005,
                    1001,
                    997,
                    990,
                    984,
                    977,
                    974,
                    972,
                    970,
                    968
                ],
                "y": [
                    407,
                    403,
                    400,
                    398,
                    400,
                    404,
                    409,
                    415,
                    419,
                    426,
                    431,
                    435,
                    436,
                    437,
                    435,
                    430,
                    428,
                    427,
                    426,
                    426,
                    425,
                    423,
                    419,
                    414,
                    412
                ]
            },
            "class": "defect",
            "case": "porosity"
        }
    ]
}