{
    "info": {
        "id": 14600295,
        "type": "VT",
        "material": "ST"
    },
    "image_data": {
        "file_name": "VT_ST_02_14600295",
        "format": "jpg",
        "information": "기공",
        "width": 1280,
        "height": 720
    },
    "meta": {
        "is_crowd": 0,
        "annotation_case": [
            "porosity"
        ],
        "total_case": [
            "porosity",
            "porosity",
            "porosity",
            "porosity",
            "porosity",
            "porosity",
            "porosity",
            "porosity",
            "porosity",
            "porosity"
        ]
    },
    "annotations": [
        {
            "tool": "polygon",
            "coordinate": {
                "x": [
                    61,
                    58,
                    55,
                    54,
                    49,
                    46,
                    45,
                    43,
                    42,
                    42,
                    44,
                    47,
                    50,
                    54,
                    55,
                    57,
                    58,
                    59
                ],
                "y": [
                    347,
                    347,
                    347,
                    346,
                    344,
                    342,
                    341,
                    338,
                    336,
                    333,
                    330,
                    327,
                    324,
                    325,
                    326,
                    330,
                    335,
                    337
                ]
            },
            "class": "defect",
            "case": "porosity"
        },
        {
            "tool": "polygon",
            "coordinate": {
                "x": [
                    65,
                    59,
                    55,
                    52,
                    54,
                    56,
                    56,
                    47,
                    38,
                    36,
                    34,
                    31,
                    27,
                    26,
                    25,
                    23,
                    22,
                    22,
                    22,
                    24,
                    24,
                    24,
                    25,
                    30,
                    32,
                    33,
                    33,
                    33,
                    36,
                    38,
                    39,
                    40,
                    40,
                    43,
                    50,
                    52,
                    54,
                    56,
                    59,
                    60
                ],
                "y": [
                    362,
                    365,
                    368,
                    372,
                    383,
                    387,
                    389,
                    392,
                    387,
                    383,
                    380,
                    376,
                    371,
                    368,
                    365,
                    357,
                    354,
                    350,
                    345,
                    342,
                    337,
                    333,
                    331,
                    327,
                    327,
                    329,
                    332,
                    334,
                    335,
                    334,
                    334,
                    336,
                    347,
                    356,
                    358,
                    356,
                    354,
                    353,
                    355,
                    356
                ]
            },
            "class": "defect",
            "case": "porosity"
        },
        {
            "tool": "polygon",
            "coordinate": {
                "x": [
                    70,
                    68,
                    66,
                    61,
                    59,
                    58,
                    58,
                    58,
                    57,
                    58,
                    59,
                    59,
                    61,
                    63,
                    67,
                    69,
                    70,
                    70
                ],
                "y": [
                    468,
                    471,
                    473,
                    474,
                    473,
                    472,
                    471,
                    469,
                    465,
                    460,
                    459,
                    459,
                    459,
                    459,
                    459,
                    460,
                    461,
                    463
                ]
            },
            "class": "defect",
            "case": "porosity"
        },
        {
            "tool": "polygon",
            "coordinate": {
                "x": [
                    406,
                    400,
                    395,
                    389,
                    385,
                    382,
                    380,
                    381,
                    381,
                    379,
                    379,
                    378,
                    376,
                    372,
                    372,
                    372,
                    375,
                    380,
                    383,
                    386,
                    391,
                    394,
                    398,
                    404,
                    407,
                    409,
                    412,
                    413,
                    413,
                    412
                ],
                "y": [
                    297,
                    298,
                    298,
                    298,
                    299,
                    298,
                    297,
                    295,
                    294,
                    291,
                    290,
                    289,
                    289,
                    290,
                    287,
                    284,
                    282,
                    282,
                    282,
                    281,
                    281,
                    280,
                    280,
                    280,
                    281,
                    282,
                    284,
                    287,
                    289,
                    293
                ]
            },
            "class": "defect",
            "case": "porosity"
        },
        {
            "tool": "polygon",
            "coordinate": {
                "x": [
                    1053,
                    1054,
                    1054,
                    1052,
                    1048,
                    1045,
                    1038,
                    1032,
                    1029,
                    1028,
                    1024,
                    1021,
                    1019,
                    1018,
                    1017,
                    1017,
                    1019,
                    1024,
                    1026,
                    1030,
                    1032,
                    1035,
                    1038,
                    1040,
                    1040,
                    1044,
                    1044,
                    1046,
                    1047,
                    1048
                ],
                "y": [
                    333,
                    339,
                    345,
                    351,
                    359,
                    363,
                    363,
                    358,
                    356,
                    354,
                    348,
                    343,
                    337,
                    335,
                    330,
                    324,
                    319,
                    315,
                    315,
                    315,
                    316,
                    319,
                    319,
                    320,
                    324,
                    327,
                    326,
                    324,
                    324,
                    325
                ]
            },
            "class": "defect",
            "case": "porosity"
        },
        {
            "tool": "polygon",
            "coordinate": {
                "x": [
                    1056,
                    1056,
                    1054,
                    1051,
                    1049,
                    1047,
                    1044,
                    1043,
                    1041,
                    1037,
                    1032,
                    1032,
                    1032,
                    1036,
                    1038,
                    1043,
                    1049,
                    1053,
                    1056,
                    1058,
                    1059,
                    1059,
                    1059,
                    1059
                ],
                "y": [
                    322,
                    322,
                    323,
                    323,
                    322,
                    321,
                    320,
                    319,
                    318,
                    316,
                    313,
                    312,
                    307,
                    303,
                    301,
                    300,
                    300,
                    301,
                    303,
                    305,
                    310,
                    312,
                    316,
                    316
                ]
            },
            "class": "defect",
            "case": "porosity"
        },
        {
            "tool": "polygon",
            "coordinate": {
                "x": [
                    1021,
                    1023,
                    1024,
                    1024,
                    1024,
                    1023,
                    1021,
                    1016,
                    1010,
                    1006,
                    1002,
                    1000,
                    999,
                    1000,
                    1002,
                    1003,
                    1004,
                    1010,
                    1013
                ],
                "y": [
                    272,
                    276,
                    278,
                    283,
                    287,
                    292,
                    295,
                    295,
                    293,
                    291,
                    287,
                    285,
                    283,
                    279,
                    274,
                    271,
                    269,
                    268,
                    268
                ]
            },
            "class": "defect",
            "case": "porosity"
        },
        {
            "tool": "polygon",
            "coordinate": {
                "x": [
                    1168,
                    1167,
                    1166,
                    1165,
                    1159,
                    1154,
                    1154,
                    1152,
                    1152,
                    1151,
                    1151,
                    1151,
                    1153,
                    1156,
                    1159,
                    1160,
                    1161,
                    1164,
                    1165,
                    1166,
                    1168
                ],
                "y": [
                    300,
                    303,
                    305,
                    307,
                    307,
                    305,
                    305,
                    304,
                    302,
                    299,
                    297,
                    294,
                    291,
                    289,
                    288,
                    288,
                    288,
                    290,
                    292,
                    294,
                    296
                ]
            },
            "class": "defect",
            "case": "porosity"
        },
        {
            "tool": "polygon",
            "coordinate": {
                "x": [
                    1087,
                    1087,
                    1087,
                    1088,
                    1087,
                    1086,
                    1083,
                    1082,
                    1080,
                    1079,
                    1079,
                    1080,
                    1081,
                    1082,
                    1084
                ],
                "y": [
                    382,
                    385,
                    388,
                    393,
                    398,
                    398,
                    396,
                    394,
                    391,
                    388,
                    385,
                    383,
                    380,
                    380,
                    380
                ]
            },
            "class": "defect",
            "case": "porosity"
        },
        {
            "tool": "polygon",
            "coordinate": {
                "x": [
                    1096,
                    1091,
                    1088,
                    1088,
                    1092,
                    1095,
                    1099,
                    1103,
                    1103,
                    1101,
                    1101
                ],
                "y": [
                    452,
                    454,
                    453,
                    445,
                    443,
                    442,
                    442,
                    443,
                    445,
                    450,
                    450
                ]
            },
            "class": "defect",
            "case": "porosity"
        }
    ]
}