{
    "info": {
        "id": 14563552,
        "type": "VT",
        "material": "ST"
    },
    "image_data": {
        "file_name": "VT_ST_00_14563552",
        "format": "jpg",
        "information": "정상",
        "width": 3840,
        "height": 2160
    },
    "meta": {
        "is_crowd": 0,
        "annotation_case": [
            "normal"
        ],
        "total_case": [
            "normal"
        ]
    },
    "annotations": [
        {
            "tool": "polygon",
            "coordinate": {
                "x": [
                    792,
                    786,
                    672,
                    666,
                    606,
                    600,
                    486,
                    480,
                    144,
                    138,
                    66,
                    60,
                    36,
                    30,
                    30,
                    24,
                    24,
                    30,
                    30,
                    252,
                    258,
                    456,
                    461,
                    701,
                    708,
                    1073,
                    1080,
                    1242,
                    1248,
                    1433,
                    1440,
                    1866,
                    1872,
                    1902,
                    1913,
                    1913,
                    1920,
                    1920,
                    1925,
                    1925,
                    1932,
                    1932,
                    1925,
                    1925,
                    1920,
                    1920,
                    1913,
                    1913,
                    1908,
                    1908,
                    1890,
                    1890,
                    1866,
                    1842,
                    1836,
                    1829,
                    1824,
                    1817,
                    1812,
                    1800,
                    1793,
                    1733,
                    1728,
                    1709,
                    1704,
                    1692,
                    1686,
                    1662,
                    1656
                ],
                "y": [
                    959,
                    965,
                    965,
                    972,
                    972,
                    978,
                    978,
                    984,
                    984,
                    989,
                    989,
                    995,
                    995,
                    1002,
                    1008,
                    1013,
                    1278,
                    1283,
                    1289,
                    1289,
                    1283,
                    1283,
                    1289,
                    1289,
                    1296,
                    1296,
                    1302,
                    1302,
                    1296,
                    1296,
                    1289,
                    1289,
                    1283,
                    1283,
                    1272,
                    1254,
                    1248,
                    1242,
                    1235,
                    1224,
                    1218,
                    1151,
                    1146,
                    1134,
                    1127,
                    1110,
                    1103,
                    1073,
                    1067,
                    1062,
                    1043,
                    1032,
                    1008,
                    1008,
                    1002,
                    1002,
                    995,
                    995,
                    989,
                    989,
                    984,
                    984,
                    978,
                    978,
                    972,
                    972,
                    965,
                    965,
                    959
                ]
            },
            "class": "normal",
            "case": ""
        }
    ]
}