{
    "info": {
        "id": 14489063,
        "type": "RT",
        "material": "AL"
    },
    "image_data": {
        "file_name": "RT_AL_02_14489063",
        "format": "jpg",
        "information": "기공",
        "width": 1280,
        "height": 720
    },
    "meta": {
        "is_crowd": 0,
        "annotation_case": [
            "porosity"
        ],
        "total_case": [
            "porosity",
            "porosity"
        ]
    },
    "annotations": [
        {
            "tool": "polygon",
            "coordinate": {
                "x": [
                    625,
                    613,
                    603,
                    594,
                    596,
                    600,
                    611,
                    624,
                    633,
                    645,
                    654,
                    661,
                    667,
                    668,
                    661,
                    660
                ],
                "y": [
                    323,
                    327,
                    333,
                    341,
                    359,
                    366,
                    376,
                    380,
                    380,
                    379,
                    373,
                    369,
                    362,
                    351,
                    333,
                    329
                ]
            },
            "class": "defect",
            "case": "porosity"
        },
        {
            "tool": "polygon",
            "coordinate": {
                "x": [
                    420,
                    414,
                    407,
                    407,
                    407,
                    407,
                    409,
                    419,
                    438,
                    452,
                    463,
                    468,
                    468,
                    463,
                    453,
                    449
                ],
                "y": [
                    246,
                    252,
                    269,
                    282,
                    294,
                    307,
                    319,
                    330,
                    333,
                    330,
                    320,
                    295,
                    282,
                    268,
                    258,
                    253
                ]
            },
            "class": "defect",
            "case": "porosity"
        }
    ]
}