{
    "info": {
        "id": 14518017,
        "type": "RT",
        "material": "ST"
    },
    "image_data": {
        "file_name": "RT_ST_01_14518017",
        "format": "jpg",
        "information": "균열",
        "width": 1280,
        "height": 720
    },
    "meta": {
        "is_crowd": 0,
        "annotation_case": [
            "crack"
        ],
        "total_case": [
            "crack",
            "crack",
            "crack"
        ]
    },
    "annotations": [
        {
            "tool": "polygon",
            "coordinate": {
                "x": [
                    1163,
                    1167,
                    1183,
                    1223,
                    1231,
                    1227,
                    1251,
                    1279,
                    1279,
                    1263,
                    1251,
                    1227,
                    1227,
                    1203
                ],
                "y": [
                    241,
                    317,
                    353,
                    409,
                    453,
                    497,
                    513,
                    513,
                    473,
                    405,
                    385,
                    325,
                    281,
                    217
                ]
            },
            "class": "defect",
            "case": "crack"
        },
        {
            "tool": "polygon",
            "coordinate": {
                "x": [
                    551,
                    591,
                    603,
                    619,
                    643,
                    755,
                    759,
                    703,
                    659,
                    643,
                    627,
                    587,
                    575
                ],
                "y": [
                    261,
                    337,
                    373,
                    425,
                    465,
                    501,
                    441,
                    421,
                    381,
                    333,
                    273,
                    237,
                    221
                ]
            },
            "class": "defect",
            "case": "crack"
        },
        {
            "tool": "polygon",
            "coordinate": {
                "x": [
                    255,
                    259,
                    271,
                    247,
                    223,
                    215,
                    247,
                    303,
                    319,
                    351,
                    367,
                    359,
                    379,
                    403,
                    383,
                    335,
                    331,
                    319,
                    303,
                    303,
                    279
                ],
                "y": [
                    365,
                    413,
                    453,
                    481,
                    501,
                    513,
                    529,
                    493,
                    529,
                    545,
                    525,
                    477,
                    445,
                    385,
                    357,
                    389,
                    425,
                    429,
                    345,
                    321,
                    297
                ]
            },
            "class": "defect",
            "case": "crack"
        }
    ]
}