{
    "info": {
        "id": 14619536,
        "type": "VT",
        "material": "ST"
    },
    "image_data": {
        "file_name": "VT_ST_04_14619536",
        "format": "jpg",
        "information": "융합불량",
        "width": 1280,
        "height": 720
    },
    "meta": {
        "is_crowd": 0,
        "annotation_case": [
            "lack of fusion"
        ],
        "total_case": [
            "lack of fusion"
        ]
    },
    "annotations": [
        {
            "tool": "polygon",
            "coordinate": {
                "x": [
                    128,
                    126,
                    104,
                    102,
                    96,
                    94,
                    86,
                    84,
                    76,
                    74,
                    70,
                    68,
                    62,
                    60,
                    54,
                    52,
                    42,
                    40,
                    34,
                    32,
                    26,
                    24,
                    18,
                    16,
                    12,
                    10,
                    10,
                    8,
                    8,
                    10,
                    10,
                    12,
                    122,
                    124,
                    173,
                    176,
                    300,
                    302,
                    397,
                    400,
                    472,
                    474,
                    544,
                    545,
                    761,
                    764,
                    764,
                    761,
                    754,
                    752,
                    744,
                    741,
                    736,
                    734,
                    732,
                    729,
                    728,
                    725,
                    721,
                    720,
                    718,
                    716,
                    714,
                    712,
                    708,
                    705,
                    701,
                    700,
                    696,
                    694,
                    689,
                    688,
                    685,
                    684,
                    680,
                    678,
                    670,
                    668,
                    661,
                    660,
                    649,
                    648,
                    637,
                    636,
                    614,
                    612,
                    574,
                    572,
                    556,
                    554,
                    529,
                    528,
                    510,
                    508,
                    494,
                    492,
                    474,
                    472,
                    452,
                    449,
                    436,
                    434,
                    425,
                    424,
                    416,
                    414,
                    409,
                    408,
                    405,
                    404,
                    397,
                    396,
                    282,
                    280
                ],
                "y": [
                    247,
                    249,
                    249,
                    251,
                    251,
                    254,
                    254,
                    256,
                    256,
                    257,
                    257,
                    259,
                    259,
                    262,
                    262,
                    264,
                    264,
                    265,
                    265,
                    267,
                    267,
                    270,
                    270,
                    272,
                    272,
                    274,
                    295,
                    298,
                    334,
                    336,
                    337,
                    339,
                    339,
                    337,
                    337,
                    336,
                    336,
                    334,
                    334,
                    331,
                    331,
                    329,
                    329,
                    328,
                    328,
                    326,
                    316,
                    313,
                    313,
                    311,
                    311,
                    310,
                    310,
                    308,
                    308,
                    306,
                    306,
                    303,
                    303,
                    301,
                    301,
                    300,
                    300,
                    298,
                    298,
                    295,
                    295,
                    293,
                    293,
                    292,
                    292,
                    290,
                    290,
                    288,
                    288,
                    285,
                    285,
                    283,
                    283,
                    282,
                    282,
                    280,
                    280,
                    277,
                    277,
                    275,
                    275,
                    274,
                    274,
                    272,
                    272,
                    270,
                    270,
                    267,
                    267,
                    265,
                    265,
                    264,
                    264,
                    262,
                    262,
                    259,
                    259,
                    257,
                    257,
                    256,
                    256,
                    254,
                    254,
                    251,
                    251,
                    249,
                    249,
                    247
                ]
            },
            "class": "defect",
            "case": "lack of fusion"
        }
    ]
}