{
    "info": {
        "id": 14550720,
        "type": "RT",
        "material": "ST"
    },
    "image_data": {
        "file_name": "RT_ST_04_14550720",
        "format": "jpg",
        "information": "융합불량",
        "width": 1280,
        "height": 720
    },
    "meta": {
        "is_crowd": 0,
        "annotation_case": [
            "lack of fusion"
        ],
        "total_case": [
            "lack of fusion"
        ]
    },
    "annotations": [
        {
            "tool": "polygon",
            "coordinate": {
                "x": [
                    82,
                    90,
                    1202,
                    1186
                ],
                "y": [
                    292,
                    412,
                    432,
                    304
                ]
            },
            "class": "defect",
            "case": "lack of fusion"
        }
    ]
}