{
    "info": {
        "id": 14487590,
        "type": "RT",
        "material": "AL"
    },
    "image_data": {
        "file_name": "RT_AL_01_14487590",
        "format": "jpg",
        "information": "균열",
        "width": 1280,
        "height": 720
    },
    "meta": {
        "is_crowd": 0,
        "annotation_case": [
            "crack"
        ],
        "total_case": [
            "crack"
        ]
    },
    "annotations": [
        {
            "tool": "polygon",
            "coordinate": {
                "x": [
                    636,
                    646,
                    651,
                    651,
                    642,
                    642,
                    642,
                    651,
                    653,
                    657,
                    658,
                    658,
                    656,
                    654,
                    655,
                    658,
                    659,
                    659,
                    656,
                    647,
                    642,
                    636,
                    629,
                    625,
                    626,
                    626,
                    627,
                    623,
                    616,
                    612,
                    603,
                    597,
                    588,
                    589,
                    585,
                    575,
                    577,
                    579,
                    588,
                    600,
                    605,
                    612,
                    618,
                    622,
                    625
                ],
                "y": [
                    437,
                    408,
                    382,
                    359,
                    348,
                    335,
                    322,
                    311,
                    305,
                    283,
                    274,
                    253,
                    233,
                    220,
                    200,
                    190,
                    175,
                    163,
                    154,
                    152,
                    157,
                    166,
                    177,
                    191,
                    210,
                    234,
                    248,
                    257,
                    269,
                    282,
                    301,
                    309,
                    328,
                    339,
                    342,
                    344,
                    374,
                    378,
                    389,
                    392,
                    400,
                    411,
                    418,
                    418,
                    417
                ]
            },
            "class": "defect",
            "case": "crack"
        }
    ]
}